helloworldTZ.py
helloworldTZ-0.0.1.dist-info/LICENSE
helloworldTZ-0.0.1.dist-info/METADATA
helloworldTZ-0.0.1.dist-info/WHEEL
helloworldTZ-0.0.1.dist-info/top_level.txt
helloworldTZ-0.0.1.dist-info/RECORD
