Metadata-Version: 2.1
Name: helloworldTZ
Version: 0.0.1
Summary: Say hello!
Home-page: http://trevorzhen.com/
Author: trevorzhen
Author-email: trevorzhen@gmail.com
License: UNKNOWN
Platform: UNKNOWN
Classifier: Programming Language :: Python :: 3
Classifier: License :: OSI Approved :: MIT License
Classifier: Intended Audience :: Developers
Classifier: Operating System :: OS Independent
License-File: LICENSE
Requires-Dist: numpy
Provides-Extra: dev
Requires-Dist: pytest (>=3.7) ; extra == 'dev'
